jarexps/__init__.py
jarexps/cli.py
jarexps/server.py
jarexps/utils.py
jarexps-0.1.26.dist-info/LICENSE
jarexps-0.1.26.dist-info/METADATA
jarexps-0.1.26.dist-info/WHEEL
jarexps-0.1.26.dist-info/entry_points.txt
jarexps-0.1.26.dist-info/top_level.txt
jarexps-0.1.26.dist-info/RECORD
