Metadata-Version: 2.1
Name: jarexps
Version: 0.1.26
Summary: Setup a simple orpc server to export services from a jar file.
Author: De Hao
Author-email: dehao@zencore.cn
Maintainer: De Hao
Maintainer-email: dehao@zencore.cn
License: MIT
Keywords: jarexps,jarexpsd
Classifier: Development Status :: 5 - Production/Stable
Classifier: Intended Audience :: Developers
Classifier: Topic :: Software Development :: Libraries :: Python Modules
Classifier: License :: OSI Approved :: MIT License
Classifier: Programming Language :: Python :: 3
Classifier: Programming Language :: Python :: 3 :: Only
License-File: LICENSE
Requires-Dist: JPype1
Requires-Dist: zenutils >=0.4.8
Requires-Dist: orpc-server >=0.5.9
